rtl/wb_fuente/ROM_fuente.v
module ROM_fuente (clk, rst, addr_rd, rd, d_out);
/*              	  ______________
	clk	-------->|	    ROM |	
	rst	-------->|		|
			 |  		|
	                 |   fuente	|				
	                 |  		|
	addr_rd -------->|	   	|-------->	d_out		
	rd	-------->|______________|				

*/

input clk, rst, rd;
input [9:0] addr_rd;       //Dirección de lectura
output reg [7:0] d_out;     //Dato de salida

reg [7:0] rom [0:563];     // 564-bit x 8-bit ROM

       	initial begin
                $readmemh("../fuente_6x8.list", rom);
        end

        always @(negedge clk) begin
		if (rst == 1'b1) begin
			d_out <= 8'd0;
		end 
		else begin
			if (rd) begin	//Lectura de la memoria ROM
				d_out <= rom[addr_rd];
			end 
		end
	end

endmodule

rtl/wb_fuente/wb_fuente.v
/*Wishbone Fuente 

Register Description:
Escritura		rd              //0x00
			addr_rd 	//0x04
Lectura			d_out		//0x08
*/


module wb_fuente(
        input              clk,
	input              reset,
	// Wishbone interface
	input              wb_stb_i,
	input              wb_cyc_i,
	output             wb_ack_o,
	input              wb_we_i,
	input       [31:0] wb_adr_i,
	input        [3:0] wb_sel_i,
	input       [31:0] wb_dat_i,
	output reg  [31:0] wb_dat_o
);


/*			   _____________
	clk	-------->|	    ROM |	
	rst	-------->|		|
			 |  		|
	                 |  ROM_fuente	|				
	                 |  		|
	addr_rd -------->|	   	|-------->	d_out		
	rd	-------->|______________|					
*/


//---------------------------------------------------------------------------
// Actual wires pantalla engine
//---------------------------------------------------------------------------

//Se declaran como registros las entradas del módulo

reg rd = 1'b0;
reg [9:0] addr_rd;

//Se declaran como wires las salidas del módulo

wire [7:0] d_out;

ROM_fuente rom0 (.clk(clk), .rst(reset), .addr_rd(addr_rd), .rd(rd), .d_out(d_out));

wire wb_rd = wb_stb_i & wb_cyc_i & ~wb_we_i;
wire wb_wr = wb_stb_i & wb_cyc_i &  wb_we_i;

reg  ack; // aún no se que es esto

assign wb_ack_o = wb_stb_i & wb_cyc_i & ack;


always @(posedge clk) begin
	if (reset) begin
		wb_dat_o[31:0] 		        <= 32'b0;
		rd				<= 1'b0;		
		addr_rd  			<= 10'b0;
		
	end else begin
		wb_dat_o[31:8] <= 24'b0;
		ack  <= 0;
		//Lectura y escritura de registros
		if (wb_rd & ~ack) begin			//Salidas del whisbone
			ack <= 1;
			wb_dat_o[7:0] <= d_out;						    //0x08
		end else if (wb_wr & ~ack ) begin 	//Entradas del whisbone
			ack 		<= 1;	
			case (wb_adr_i[3:2]) 
			3'b00: begin 	        rd  		<= wb_dat_i[0]; 	end //0x00
			3'b01: begin		addr_rd		<= wb_dat_i[9:0]; 	end //0x04
			default: begin 	        wb_dat_o[7:0]   <= 8'b0; 		end
			endcase
		end
	end
end

endmodule

rtl/wb_fuente/wb_fuente_TB.v
`timescale 10ns / 10ps
`define SIMULATION

module wb_fuente_TB;

	reg  clk;
   	reg  rst;
   
   	reg              	wb_stb_i;
	reg              	wb_cyc_i;
	wire             	wb_ack_o;
	reg              	wb_we_i;
	reg       	[31:0] wb_adr_i;
	reg        	[3:0] 	wb_sel_i;
	reg       	[31:0] wb_dat_i;
	wire  		[31:0] wb_dat_o;
   	
   	wb_fuente test (clk, rst, wb_stb_i, wb_cyc_i, wb_ack_o, wb_we_i, wb_adr_i, wb_sel_i, wb_dat_i, wb_dat_o);
   	
	always #1 clk = ~clk; 
	
	initial begin
        	#1000
       	$finish;
   	end
	
	initial begin  // Initialize Inputs
		clk 		= 0; 
		rst 		= 0;
		wb_stb_i	= 0;
		wb_cyc_i	= 0;
		wb_we_i	= 0;
		wb_adr_i	= 0;
		wb_sel_i	= 0;
		wb_dat_i	= 0;
	end
	
	initial begin
		#10
		rst = 1'b1;
		#10
		rst = 1'b0;
		#10
		wb_dat_i = 32'h00000038;
		wb_adr_i = 32'h00000004;
		#10
		wb_stb_i = 1'b1;
		wb_cyc_i = 1'b1;
		wb_we_i  = 1'b1;
		#4
		wb_stb_i = 1'b0;
		wb_cyc_i = 1'b0;
		wb_we_i  = 1'b0;
		#10
		wb_dat_i = 32'h00000001;
		wb_adr_i = 32'h00000000;
		#10
		wb_stb_i = 1'b1;
		wb_cyc_i = 1'b1;
		wb_we_i  = 1'b1;
		#4
		wb_stb_i = 1'b0;
		wb_cyc_i = 1'b0;
		wb_we_i  = 1'b0;
		#10
		wb_dat_i = 32'h00000000;
		wb_adr_i = 32'h00000000;
		#10
		wb_stb_i = 1'b1;
		wb_cyc_i = 1'b1;
		wb_we_i  = 1'b1;
		#4
		wb_stb_i = 1'b0;
		wb_cyc_i = 1'b0;
		wb_we_i  = 1'b0;
		#10
		wb_dat_i = 32'h00000000;
		wb_adr_i = 32'h00000008;
		#10
		wb_stb_i = 1'b1;
		wb_cyc_i = 1'b1;
		wb_we_i  = 1'b0;
		#4
		wb_stb_i = 1'b0;
		wb_cyc_i = 1'b0;
		wb_we_i  = 1'b0;
	end
		
	initial begin
     		$dumpfile("wb_fuente_TB.vcd");
     		$dumpvars(-1, test);
   	end

endmodule

rtl/wb_fuente/simulation/wb_fuente_TB.vcd
$date
	Mon May  8 14:46:43 2017
$end
$version
	Icarus Verilog
$end
$timescale
	10ps
$end
$scope module wb_fuente_TB $end
$scope module test $end
$var wire 1 ! clk $end
$var wire 8 " d_out [7:0] $end
$var wire 1 # reset $end
$var wire 1 $ wb_ack_o $end
$var wire 32 % wb_adr_i [31:0] $end
$var wire 1 & wb_cyc_i $end
$var wire 32 ' wb_dat_i [31:0] $end
$var wire 1 ( wb_rd $end
$var wire 4 ) wb_sel_i [3:0] $end
$var wire 1 * wb_stb_i $end
$var wire 1 + wb_we_i $end
$var wire 1 , wb_wr $end
$var reg 1 - ack $end
$var reg 10 . addr_rd [9:0] $end
$var reg 1 / rd $end
$var reg 32 0 wb_dat_o [31:0] $end
$scope module rom0 $end
$var wire 10 1 addr_rd [9:0] $end
$var wire 1 ! clk $end
$var wire 1 2 rd $end
$var wire 1 # rst $end
$var reg 8 3 d_out [7:0] $end
$upscope $end
$upscope $end
$upscope $end
$enddefinitions $end
#0
$dumpvars
bx 3
02
bx 1
bx 0
0/
bx .
x-
0,
0+
0*
b0 )
0(
b0 '
0&
b0 %
0$
0#
bx "
0!
$end
#1000
0-
b0xxxxxxxx 0
1!
#2000
0!
#3000
b0xxxxxxxx 0
1!
#4000
0!
#5000
b0xxxxxxxx 0
1!
#6000
0!
#7000
b0xxxxxxxx 0
1!
#8000
0!
#9000
b0xxxxxxxx 0
1!
#10000
b0 3
b0 "
0!
1#
#11000
b0 .
b0 1
b0 0
1!
#12000
0!
#13000
1!
#14000
0!
#15000
1!
#16000
0!
#17000
1!
#18000
0!
#19000
1!
#20000
0!
0#
#21000
b0 0
1!
#22000
0!
#23000
b0 0
1!
#24000
0!
#25000
b0 0
1!
#26000
0!
#27000
b0 0
1!
#28000
0!
#29000
b0 0
1!
#30000
0!
b100 %
b111000 '
#31000
b0 0
1!
#32000
0!
#33000
b0 0
1!
#34000
0!
#35000
b0 0
1!
#36000
0!
#37000
b0 0
1!
#38000
0!
#39000
b0 0
1!
#40000
1,
0!
1+
1&
1*
#41000
1$
b111000 .
b111000 1
1-
b0 0
1!
#42000
0!
#43000
0$
0-
b0 0
1!
#44000
0,
0!
0+
0&
0*
#45000
b0 0
1!
#46000
0!
#47000
b0 0
1!
#48000
0!
#49000
b0 0
1!
#50000
0!
#51000
b0 0
1!
#52000
0!
#53000
b0 0
1!
#54000
0!
b0 %
b1 '
#55000
b0 0
1!
#56000
0!
#57000
b0 0
1!
#58000
0!
#59000
b0 0
1!
#60000
0!
#61000
b0 0
1!
#62000
0!
#63000
b0 0
1!
#64000
1,
0!
1+
1&
1*
#65000
1$
1/
12
1-
b0 0
1!
#66000
b1000001 3
b1000001 "
0!
#67000
0$
0-
b0 0
1!
#68000
0,
0!
0+
0&
0*
#69000
b0 0
1!
#70000
0!
#71000
b0 0
1!
#72000
0!
#73000
b0 0
1!
#74000
0!
#75000
b0 0
1!
#76000
0!
#77000
b0 0
1!
#78000
0!
b0 '
#79000
b0 0
1!
#80000
0!
#81000
b0 0
1!
#82000
0!
#83000
b0 0
1!
#84000
0!
#85000
b0 0
1!
#86000
0!
#87000
b0 0
1!
#88000
1,
0!
1+
1&
1*
#89000
1$
0/
02
1-
b0 0
1!
#90000
0!
#91000
0$
0-
b0 0
1!
#92000
0,
0!
0+
0&
0*
#93000
b0 0
1!
#94000
0!
#95000
b0 0
1!
#96000
0!
#97000
b0 0
1!
#98000
0!
#99000
b0 0
1!
#100000
0!
#101000
b0 0
1!
#102000
0!
b1000 %
#103000
b0 0
1!
#104000
0!
#105000
b0 0
1!
#106000
0!
#107000
b0 0
1!
#108000
0!
#109000
b0 0
1!
#110000
0!
#111000
b0 0
1!
#112000
1(
0!
1&
1*
#113000
1$
1-
b1000001 0
1!
#114000
0!
#115000
0$
0-
b1000001 0
1!
#116000
0(
0!
0&
0*
#117000
b1000001 0
1!
#118000
0!
#119000
b1000001 0
1!
#120000
0!
#121000
b1000001 0
1!
#122000
0!
#123000
b1000001 0
1!
#124000
0!
#125000
b1000001 0
1!
#126000
0!
#127000
b1000001 0
1!
#128000
0!
#129000
b1000001 0
1!
#130000
0!
#131000
b1000001 0
1!
#132000
0!
#133000
b1000001 0
1!
#134000
0!
#135000
b1000001 0
1!
#136000
0!
#137000
b1000001 0
1!
#138000
0!
#139000
b1000001 0
1!
#140000
0!
#141000
b1000001 0
1!
#142000
0!
#143000
b1000001 0
1!
#144000
0!
#145000
b1000001 0
1!
#146000
0!
#147000
b1000001 0
1!
#148000
0!
#149000
b1000001 0
1!
#150000
0!
#151000
b1000001 0
1!
#152000
0!
#153000
b1000001 0
1!
#154000
0!
#155000
b1000001 0
1!
#156000
0!
#157000
b1000001 0
1!
#158000
0!
#159000
b1000001 0
1!
#160000
0!
#161000
b1000001 0
1!
#162000
0!
#163000
b1000001 0
1!
#164000
0!
#165000
b1000001 0
1!
#166000
0!
#167000
b1000001 0
1!
#168000
0!
#169000
b1000001 0
1!
#170000
0!
#171000
b1000001 0
1!
#172000
0!
#173000
b1000001 0
1!
#174000
0!
#175000
b1000001 0
1!
#176000
0!
#177000
b1000001 0
1!
#178000
0!
#179000
b1000001 0
1!
#180000
0!
#181000
b1000001 0
1!
#182000
0!
#183000
b1000001 0
1!
#184000
0!
#185000
b1000001 0
1!
#186000
0!
#187000
b1000001 0
1!
#188000
0!
#189000
b1000001 0
1!
#190000
0!
#191000
b1000001 0
1!
#192000
0!
#193000
b1000001 0
1!
#194000
0!
#195000
b1000001 0
1!
#196000
0!
#197000
b1000001 0
1!
#198000
0!
#199000
b1000001 0
1!
#200000
0!
#201000
b1000001 0
1!
#202000
0!
#203000
b1000001 0
1!
#204000
0!
#205000
b1000001 0
1!
#206000
0!
#207000
b1000001 0
1!
#208000
0!
#209000
b1000001 0
1!
#210000
0!
#211000
b1000001 0
1!
#212000
0!
#213000
b1000001 0
1!
#214000
0!
#215000
b1000001 0
1!
#216000
0!
#217000
b1000001 0
1!
#218000
0!
#219000
b1000001 0
1!
#220000
0!
#221000
b1000001 0
1!
#222000
0!
#223000
b1000001 0
1!
#224000
0!
#225000
b1000001 0
1!
#226000
0!
#227000
b1000001 0
1!
#228000
0!
#229000
b1000001 0
1!
#230000
0!
#231000
b1000001 0
1!
#232000
0!
#233000
b1000001 0
1!
#234000
0!
#235000
b1000001 0
1!
#236000
0!
#237000
b1000001 0
1!
#238000
0!
#239000
b1000001 0
1!
#240000
0!
#241000
b1000001 0
1!
#242000
0!
#243000
b1000001 0
1!
#244000
0!
#245000
b1000001 0
1!
#246000
0!
#247000
b1000001 0
1!
#248000
0!
#249000
b1000001 0
1!
#250000
0!
#251000
b1000001 0
1!
#252000
0!
#253000
b1000001 0
1!
#254000
0!
#255000
b1000001 0
1!
#256000
0!
#257000
b1000001 0
1!
#258000
0!
#259000
b1000001 0
1!
#260000
0!
#261000
b1000001 0
1!
#262000
0!
#263000
b1000001 0
1!
#264000
0!
#265000
b1000001 0
1!
#266000
0!
#267000
b1000001 0
1!
#268000
0!
#269000
b1000001 0
1!
#270000
0!
#271000
b1000001 0
1!
#272000
0!
#273000
b1000001 0
1!
#274000
0!
#275000
b1000001 0
1!
#276000
0!
#277000
b1000001 0
1!
#278000
0!
#279000
b1000001 0
1!
#280000
0!
#281000
b1000001 0
1!
#282000
0!
#283000
b1000001 0
1!
#284000
0!
#285000
b1000001 0
1!
#286000
0!
#287000
b1000001 0
1!
#288000
0!
#289000
b1000001 0
1!
#290000
0!
#291000
b1000001 0
1!
#292000
0!
#293000
b1000001 0
1!
#294000
0!
#295000
b1000001 0
1!
#296000
0!
#297000
b1000001 0
1!
#298000
0!
#299000
b1000001 0
1!
#300000
0!
#301000
b1000001 0
1!
#302000
0!
#303000
b1000001 0
1!
#304000
0!
#305000
b1000001 0
1!
#306000
0!
#307000
b1000001 0
1!
#308000
0!
#309000
b1000001 0
1!
#310000
0!
#311000
b1000001 0
1!
#312000
0!
#313000
b1000001 0
1!
#314000
0!
#315000
b1000001 0
1!
#316000
0!
#317000
b1000001 0
1!
#318000
0!
#319000
b1000001 0
1!
#320000
0!
#321000
b1000001 0
1!
#322000
0!
#323000
b1000001 0
1!
#324000
0!
#325000
b1000001 0
1!
#326000
0!
#327000
b1000001 0
1!
#328000
0!
#329000
b1000001 0
1!
#330000
0!
#331000
b1000001 0
1!
#332000
0!
#333000
b1000001 0
1!
#334000
0!
#335000
b1000001 0
1!
#336000
0!
#337000
b1000001 0
1!
#338000
0!
#339000
b1000001 0
1!
#340000
0!
#341000
b1000001 0
1!
#342000
0!
#343000
b1000001 0
1!
#344000
0!
#345000
b1000001 0
1!
#346000
0!
#347000
b1000001 0
1!
#348000
0!
#349000
b1000001 0
1!
#350000
0!
#351000
b1000001 0
1!
#352000
0!
#353000
b1000001 0
1!
#354000
0!
#355000
b1000001 0
1!
#356000
0!
#357000
b1000001 0
1!
#358000
0!
#359000
b1000001 0
1!
#360000
0!
#361000
b1000001 0
1!
#362000
0!
#363000
b1000001 0
1!
#364000
0!
#365000
b1000001 0
1!
#366000
0!
#367000
b1000001 0
1!
#368000
0!
#369000
b1000001 0
1!
#370000
0!
#371000
b1000001 0
1!
#372000
0!
#373000
b1000001 0
1!
#374000
0!
#375000
b1000001 0
1!
#376000
0!
#377000
b1000001 0
1!
#378000
0!
#379000
b1000001 0
1!
#380000
0!
#381000
b1000001 0
1!
#382000
0!
#383000
b1000001 0
1!
#384000
0!
#385000
b1000001 0
1!
#386000
0!
#387000
b1000001 0
1!
#388000
0!
#389000
b1000001 0
1!
#390000
0!
#391000
b1000001 0
1!
#392000
0!
#393000
b1000001 0
1!
#394000
0!
#395000
b1000001 0
1!
#396000
0!
#397000
b1000001 0
1!
#398000
0!
#399000
b1000001 0
1!
#400000
0!
#401000
b1000001 0
1!
#402000
0!
#403000
b1000001 0
1!
#404000
0!
#405000
b1000001 0
1!
#406000
0!
#407000
b1000001 0
1!
#408000
0!
#409000
b1000001 0
1!
#410000
0!
#411000
b1000001 0
1!
#412000
0!
#413000
b1000001 0
1!
#414000
0!
#415000
b1000001 0
1!
#416000
0!
#417000
b1000001 0
1!
#418000
0!
#419000
b1000001 0
1!
#420000
0!
#421000
b1000001 0
1!
#422000
0!
#423000
b1000001 0
1!
#424000
0!
#425000
b1000001 0
1!
#426000
0!
#427000
b1000001 0
1!
#428000
0!
#429000
b1000001 0
1!
#430000
0!
#431000
b1000001 0
1!
#432000
0!
#433000
b1000001 0
1!
#434000
0!
#435000
b1000001 0
1!
#436000
0!
#437000
b1000001 0
1!
#438000
0!
#439000
b1000001 0
1!
#440000
0!
#441000
b1000001 0
1!
#442000
0!
#443000
b1000001 0
1!
#444000
0!
#445000
b1000001 0
1!
#446000
0!
#447000
b1000001 0
1!
#448000
0!
#449000
b1000001 0
1!
#450000
0!
#451000
b1000001 0
1!
#452000
0!
#453000
b1000001 0
1!
#454000
0!
#455000
b1000001 0
1!
#456000
0!
#457000
b1000001 0
1!
#458000
0!
#459000
b1000001 0
1!
#460000
0!
#461000
b1000001 0
1!
#462000
0!
#463000
b1000001 0
1!
#464000
0!
#465000
b1000001 0
1!
#466000
0!
#467000
b1000001 0
1!
#468000
0!
#469000
b1000001 0
1!
#470000
0!
#471000
b1000001 0
1!
#472000
0!
#473000
b1000001 0
1!
#474000
0!
#475000
b1000001 0
1!
#476000
0!
#477000
b1000001 0
1!
#478000
0!
#479000
b1000001 0
1!
#480000
0!
#481000
b1000001 0
1!
#482000
0!
#483000
b1000001 0
1!
#484000
0!
#485000
b1000001 0
1!
#486000
0!
#487000
b1000001 0
1!
#488000
0!
#489000
b1000001 0
1!
#490000
0!
#491000
b1000001 0
1!
#492000
0!
#493000
b1000001 0
1!
#494000
0!
#495000
b1000001 0
1!
#496000
0!
#497000
b1000001 0
1!
#498000
0!
#499000
b1000001 0
1!
#500000
0!
#501000
b1000001 0
1!
#502000
0!
#503000
b1000001 0
1!
#504000
0!
#505000
b1000001 0
1!
#506000
0!
#507000
b1000001 0
1!
#508000
0!
#509000
b1000001 0
1!
#510000
0!
#511000
b1000001 0
1!
#512000
0!
#513000
b1000001 0
1!
#514000
0!
#515000
b1000001 0
1!
#516000
0!
#517000
b1000001 0
1!
#518000
0!
#519000
b1000001 0
1!
#520000
0!
#521000
b1000001 0
1!
#522000
0!
#523000
b1000001 0
1!
#524000
0!
#525000
b1000001 0
1!
#526000
0!
#527000
b1000001 0
1!
#528000
0!
#529000
b1000001 0
1!
#530000
0!
#531000
b1000001 0
1!
#532000
0!
#533000
b1000001 0
1!
#534000
0!
#535000
b1000001 0
1!
#536000
0!
#537000
b1000001 0
1!
#538000
0!
#539000
b1000001 0
1!
#540000
0!
#541000
b1000001 0
1!
#542000
0!
#543000
b1000001 0
1!
#544000
0!
#545000
b1000001 0
1!
#546000
0!
#547000
b1000001 0
1!
#548000
0!
#549000
b1000001 0
1!
#550000
0!
#551000
b1000001 0
1!
#552000
0!
#553000
b1000001 0
1!
#554000
0!
#555000
b1000001 0
1!
#556000
0!
#557000
b1000001 0
1!
#558000
0!
#559000
b1000001 0
1!
#560000
0!
#561000
b1000001 0
1!
#562000
0!
#563000
b1000001 0
1!
#564000
0!
#565000
b1000001 0
1!
#566000
0!
#567000
b1000001 0
1!
#568000
0!
#569000
b1000001 0
1!
#570000
0!
#571000
b1000001 0
1!
#572000
0!
#573000
b1000001 0
1!
#574000
0!
#575000
b1000001 0
1!
#576000
0!
#577000
b1000001 0
1!
#578000
0!
#579000
b1000001 0
1!
#580000
0!
#581000
b1000001 0
1!
#582000
0!
#583000
b1000001 0
1!
#584000
0!
#585000
b1000001 0
1!
#586000
0!
#587000
b1000001 0
1!
#588000
0!
#589000
b1000001 0
1!
#590000
0!
#591000
b1000001 0
1!
#592000
0!
#593000
b1000001 0
1!
#594000
0!
#595000
b1000001 0
1!
#596000
0!
#597000
b1000001 0
1!
#598000
0!
#599000
b1000001 0
1!
#600000
0!
#601000
b1000001 0
1!
#602000
0!
#603000
b1000001 0
1!
#604000
0!
#605000
b1000001 0
1!
#606000
0!
#607000
b1000001 0
1!
#608000
0!
#609000
b1000001 0
1!
#610000
0!
#611000
b1000001 0
1!
#612000
0!
#613000
b1000001 0
1!
#614000
0!
#615000
b1000001 0
1!
#616000
0!
#617000
b1000001 0
1!
#618000
0!
#619000
b1000001 0
1!
#620000
0!
#621000
b1000001 0
1!
#622000
0!
#623000
b1000001 0
1!
#624000
0!
#625000
b1000001 0
1!
#626000
0!
#627000
b1000001 0
1!
#628000
0!
#629000
b1000001 0
1!
#630000
0!
#631000
b1000001 0
1!
#632000
0!
#633000
b1000001 0
1!
#634000
0!
#635000
b1000001 0
1!
#636000
0!
#637000
b1000001 0
1!
#638000
0!
#639000
b1000001 0
1!
#640000
0!
#641000
b1000001 0
1!
#642000
0!
#643000
b1000001 0
1!
#644000
0!
#645000
b1000001 0
1!
#646000
0!
#647000
b1000001 0
1!
#648000
0!
#649000
b1000001 0
1!
#650000
0!
#651000
b1000001 0
1!
#652000
0!
#653000
b1000001 0
1!
#654000
0!
#655000
b1000001 0
1!
#656000
0!
#657000
b1000001 0
1!
#658000
0!
#659000
b1000001 0
1!
#660000
0!
#661000
b1000001 0
1!
#662000
0!
#663000
b1000001 0
1!
#664000
0!
#665000
b1000001 0
1!
#666000
0!
#667000
b1000001 0
1!
#668000
0!
#669000
b1000001 0
1!
#670000
0!
#671000
b1000001 0
1!
#672000
0!
#673000
b1000001 0
1!
#674000
0!
#675000
b1000001 0
1!
#676000
0!
#677000
b1000001 0
1!
#678000
0!
#679000
b1000001 0
1!
#680000
0!
#681000
b1000001 0
1!
#682000
0!
#683000
b1000001 0
1!
#684000
0!
#685000
b1000001 0
1!
#686000
0!
#687000
b1000001 0
1!
#688000
0!
#689000
b1000001 0
1!
#690000
0!
#691000
b1000001 0
1!
#692000
0!
#693000
b1000001 0
1!
#694000
0!
#695000
b1000001 0
1!
#696000
0!
#697000
b1000001 0
1!
#698000
0!
#699000
b1000001 0
1!
#700000
0!
#701000
b1000001 0
1!
#702000
0!
#703000
b1000001 0
1!
#704000
0!
#705000
b1000001 0
1!
#706000
0!
#707000
b1000001 0
1!
#708000
0!
#709000
b1000001 0
1!
#710000
0!
#711000
b1000001 0
1!
#712000
0!
#713000
b1000001 0
1!
#714000
0!
#715000
b1000001 0
1!
#716000
0!
#717000
b1000001 0
1!
#718000
0!
#719000
b1000001 0
1!
#720000
0!
#721000
b1000001 0
1!
#722000
0!
#723000
b1000001 0
1!
#724000
0!
#725000
b1000001 0
1!
#726000
0!
#727000
b1000001 0
1!
#728000
0!
#729000
b1000001 0
1!
#730000
0!
#731000
b1000001 0
1!
#732000
0!
#733000
b1000001 0
1!
#734000
0!
#735000
b1000001 0
1!
#736000
0!
#737000
b1000001 0
1!
#738000
0!
#739000
b1000001 0
1!
#740000
0!
#741000
b1000001 0
1!
#742000
0!
#743000
b1000001 0
1!
#744000
0!
#745000
b1000001 0
1!
#746000
0!
#747000
b1000001 0
1!
#748000
0!
#749000
b1000001 0
1!
#750000
0!
#751000
b1000001 0
1!
#752000
0!
#753000
b1000001 0
1!
#754000
0!
#755000
b1000001 0
1!
#756000
0!
#757000
b1000001 0
1!
#758000
0!
#759000
b1000001 0
1!
#760000
0!
#761000
b1000001 0
1!
#762000
0!
#763000
b1000001 0
1!
#764000
0!
#765000
b1000001 0
1!
#766000
0!
#767000
b1000001 0
1!
#768000
0!
#769000
b1000001 0
1!
#770000
0!
#771000
b1000001 0
1!
#772000
0!
#773000
b1000001 0
1!
#774000
0!
#775000
b1000001 0
1!
#776000
0!
#777000
b1000001 0
1!
#778000
0!
#779000
b1000001 0
1!
#780000
0!
#781000
b1000001 0
1!
#782000
0!
#783000
b1000001 0
1!
#784000
0!
#785000
b1000001 0
1!
#786000
0!
#787000
b1000001 0
1!
#788000
0!
#789000
b1000001 0
1!
#790000
0!
#791000
b1000001 0
1!
#792000
0!
#793000
b1000001 0
1!
#794000
0!
#795000
b1000001 0
1!
#796000
0!
#797000
b1000001 0
1!
#798000
0!
#799000
b1000001 0
1!
#800000
0!
#801000
b1000001 0
1!
#802000
0!
#803000
b1000001 0
1!
#804000
0!
#805000
b1000001 0
1!
#806000
0!
#807000
b1000001 0
1!
#808000
0!
#809000
b1000001 0
1!
#810000
0!
#811000
b1000001 0
1!
#812000
0!
#813000
b1000001 0
1!
#814000
0!
#815000
b1000001 0
1!
#816000
0!
#817000
b1000001 0
1!
#818000
0!
#819000
b1000001 0
1!
#820000
0!
#821000
b1000001 0
1!
#822000
0!
#823000
b1000001 0
1!
#824000
0!
#825000
b1000001 0
1!
#826000
0!
#827000
b1000001 0
1!
#828000
0!
#829000
b1000001 0
1!
#830000
0!
#831000
b1000001 0
1!
#832000
0!
#833000
b1000001 0
1!
#834000
0!
#835000
b1000001 0
1!
#836000
0!
#837000
b1000001 0
1!
#838000
0!
#839000
b1000001 0
1!
#840000
0!
#841000
b1000001 0
1!
#842000
0!
#843000
b1000001 0
1!
#844000
0!
#845000
b1000001 0
1!
#846000
0!
#847000
b1000001 0
1!
#848000
0!
#849000
b1000001 0
1!
#850000
0!
#851000
b1000001 0
1!
#852000
0!
#853000
b1000001 0
1!
#854000
0!
#855000
b1000001 0
1!
#856000
0!
#857000
b1000001 0
1!
#858000
0!
#859000
b1000001 0
1!
#860000
0!
#861000
b1000001 0
1!
#862000
0!
#863000
b1000001 0
1!
#864000
0!
#865000
b1000001 0
1!
#866000
0!
#867000
b1000001 0
1!
#868000
0!
#869000
b1000001 0
1!
#870000
0!
#871000
b1000001 0
1!
#872000
0!
#873000
b1000001 0
1!
#874000
0!
#875000
b1000001 0
1!
#876000
0!
#877000
b1000001 0
1!
#878000
0!
#879000
b1000001 0
1!
#880000
0!
#881000
b1000001 0
1!
#882000
0!
#883000
b1000001 0
1!
#884000
0!
#885000
b1000001 0
1!
#886000
0!
#887000
b1000001 0
1!
#888000
0!
#889000
b1000001 0
1!
#890000
0!
#891000
b1000001 0
1!
#892000
0!
#893000
b1000001 0
1!
#894000
0!
#895000
b1000001 0
1!
#896000
0!
#897000
b1000001 0
1!
#898000
0!
#899000
b1000001 0
1!
#900000
0!
#901000
b1000001 0
1!
#902000
0!
#903000
b1000001 0
1!
#904000
0!
#905000
b1000001 0
1!
#906000
0!
#907000
b1000001 0
1!
#908000
0!
#909000
b1000001 0
1!
#910000
0!
#911000
b1000001 0
1!
#912000
0!
#913000
b1000001 0
1!
#914000
0!
#915000
b1000001 0
1!
#916000
0!
#917000
b1000001 0
1!
#918000
0!
#919000
b1000001 0
1!
#920000
0!
#921000
b1000001 0
1!
#922000
0!
#923000
b1000001 0
1!
#924000
0!
#925000
b1000001 0
1!
#926000
0!
#927000
b1000001 0
1!
#928000
0!
#929000
b1000001 0
1!
#930000
0!
#931000
b1000001 0
1!
#932000
0!
#933000
b1000001 0
1!
#934000
0!
#935000
b1000001 0
1!
#936000
0!
#937000
b1000001 0
1!
#938000
0!
#939000
b1000001 0
1!
#940000
0!
#941000
b1000001 0
1!
#942000
0!
#943000
b1000001 0
1!
#944000
0!
#945000
b1000001 0
1!
#946000
0!
#947000
b1000001 0
1!
#948000
0!
#949000
b1000001 0
1!
#950000
0!
#951000
b1000001 0
1!
#952000
0!
#953000
b1000001 0
1!
#954000
0!
#955000
b1000001 0
1!
#956000
0!
#957000
b1000001 0
1!
#958000
0!
#959000
b1000001 0
1!
#960000
0!
#961000
b1000001 0
1!
#962000
0!
#963000
b1000001 0
1!
#964000
0!
#965000
b1000001 0
1!
#966000
0!
#967000
b1000001 0
1!
#968000
0!
#969000
b1000001 0
1!
#970000
0!
#971000
b1000001 0
1!
#972000
0!
#973000
b1000001 0
1!
#974000
0!
#975000
b1000001 0
1!
#976000
0!
#977000
b1000001 0
1!
#978000
0!
#979000
b1000001 0
1!
#980000
0!
#981000
b1000001 0
1!
#982000
0!
#983000
b1000001 0
1!
#984000
0!
#985000
b1000001 0
1!
#986000
0!
#987000
b1000001 0
1!
#988000
0!
#989000
b1000001 0
1!
#990000
0!
#991000
b1000001 0
1!
#992000
0!
#993000
b1000001 0
1!
#994000
0!
#995000
b1000001 0
1!
#996000
0!
#997000
b1000001 0
1!
#998000
0!
#999000
b1000001 0
1!
